odoo/addons/account_invoice_import_facturx/README.rst
odoo/addons/account_invoice_import_facturx/__init__.py
odoo/addons/account_invoice_import_facturx/__manifest__.py
odoo/addons/account_invoice_import_facturx/demo/demo_data.xml
odoo/addons/account_invoice_import_facturx/i18n/account_invoice_import_facturx.pot
odoo/addons/account_invoice_import_facturx/i18n/de.po
odoo/addons/account_invoice_import_facturx/i18n/es.po
odoo/addons/account_invoice_import_facturx/i18n/fr.po
odoo/addons/account_invoice_import_facturx/i18n/it.po
odoo/addons/account_invoice_import_facturx/i18n/sl.po
odoo/addons/account_invoice_import_facturx/readme/CONTRIBUTORS.md
odoo/addons/account_invoice_import_facturx/readme/DESCRIPTION.md
odoo/addons/account_invoice_import_facturx/readme/INSTALL.md
odoo/addons/account_invoice_import_facturx/static/description/icon.png
odoo/addons/account_invoice_import_facturx/static/description/index.html
odoo/addons/account_invoice_import_facturx/tests/__init__.py
odoo/addons/account_invoice_import_facturx/tests/test_facturx.py
odoo/addons/account_invoice_import_facturx/tests/files/Facture_FR_BASIC.pdf
odoo/addons/account_invoice_import_facturx/tests/files/Facture_FR_BASICWL.pdf
odoo/addons/account_invoice_import_facturx/tests/files/Facture_FR_EN16931.pdf
odoo/addons/account_invoice_import_facturx/tests/files/Facture_FR_EXTENDED.pdf
odoo/addons/account_invoice_import_facturx/tests/files/Facture_FR_MINIMUM.pdf
odoo/addons/account_invoice_import_facturx/tests/files/ZUGFeRD_1p0_BASIC_Einfach.pdf
odoo/addons/account_invoice_import_facturx/tests/files/ZUGFeRD_1p0_BASIC_Rechnungskorrektur.pdf
odoo/addons/account_invoice_import_facturx/tests/files/ZUGFeRD_1p0_COMFORT_Einfach.pdf
odoo/addons/account_invoice_import_facturx/tests/files/ZUGFeRD_1p0_COMFORT_Einfach.pdf-ZUGFeRD-invoice.xml
odoo/addons/account_invoice_import_facturx/tests/files/ZUGFeRD_1p0_COMFORT_Haftpflichtversicherung_Versicherungssteuer.pdf
odoo_addon_account_invoice_import_facturx-18.0.1.0.0.4.dist-info/METADATA
odoo_addon_account_invoice_import_facturx-18.0.1.0.0.4.dist-info/WHEEL
odoo_addon_account_invoice_import_facturx-18.0.1.0.0.4.dist-info/top_level.txt
odoo_addon_account_invoice_import_facturx-18.0.1.0.0.4.dist-info/RECORD
